{
   "absolute_quantity": {
      "lower_bound": 374.3,
      "type": "uniform_real",
      "units": "milligram",
      "upper_bound": 375.3
   },
   "file_links": [],
   "labels": [],
   "mass_fraction": null,
   "material": {
      "id": "58afca49-4d75-4279-87a4-fa68623601fd",
      "scope": "auto",
      "type": "link_by_uid"
   },
   "name": "GBM1003B Ingredient",
   "notes": null,
   "number_fraction": null,
   "process": {
      "id": "41187fe5-9f8a-44fa-828c-b07d8743e03d",
      "scope": "auto",
      "type": "link_by_uid"
   },
   "spec": {
      "id": "86f787f4-5f59-40ad-a707-6dcd863dde8b",
      "scope": "auto",
      "type": "link_by_uid"
   },
   "tags": [],
   "type": "ingredient_run",
   "uids": {
      "auto": "a450c754-755f-4b7a-b076-2e8fdee35704"
   },
   "volume_fraction": null
}