{
   "conditions": [
      {
         "file_links": [],
         "name": "Location",
         "notes": null,
         "origin": "unknown",
         "template": {
            "id": "ee07cdac-b7ae-44e6-8601-d7e32dc30232",
            "scope": "auto",
            "type": "link_by_uid"
         },
         "type": "condition",
         "value": {
            "category": "Hot Lab",
            "type": "nominal_categorical"
         }
      }
   ],
   "file_links": [],
   "name": "GBM1009_Flux_Medium Grinding Process",
   "notes": null,
   "parameters": [
      {
         "file_links": [],
         "name": "Equipment Used",
         "notes": null,
         "origin": "unknown",
         "template": {
            "id": "9fd45261-8ac0-4e11-9f76-6fe4c1730f28",
            "scope": "auto",
            "type": "link_by_uid"
         },
         "type": "parameter",
         "value": {
            "category": "Mortar and Pestle",
            "type": "nominal_categorical"
         }
      }
   ],
   "source": {
      "performed_by": "gmurra12@jh.edu",
      "performed_date": "2023-06-23T00:00:00",
      "type": "performed_source"
   },
   "spec": {
      "id": "776b5449-535f-4fb2-8070-a9c20f378dd9",
      "scope": "auto",
      "type": "link_by_uid"
   },
   "tags": [],
   "type": "process_run",
   "uids": {
      "auto": "7af23a9d-1f00-49fc-a020-d132e759ca7f"
   }
}