{
   "absolute_quantity": {
      "lower_bound": 358.9,
      "type": "uniform_real",
      "units": "milligram",
      "upper_bound": 359.9
   },
   "file_links": [],
   "labels": [],
   "mass_fraction": null,
   "material": {
      "id": "65aceac9-b31c-4475-9399-6278eee07fda",
      "scope": "auto",
      "type": "link_by_uid"
   },
   "name": "GBM1005A Ingredient",
   "notes": null,
   "number_fraction": null,
   "process": {
      "id": "6b453f8d-45a9-4af2-ba87-4f21c70e6587",
      "scope": "auto",
      "type": "link_by_uid"
   },
   "spec": {
      "id": "1288d5a0-04e3-48de-bdf7-592432fa122a",
      "scope": "auto",
      "type": "link_by_uid"
   },
   "tags": [
      "method::crucible",
      "provenance::GBM"
   ],
   "type": "ingredient_run",
   "uids": {
      "auto": "5ad7be50-7236-4ff8-aae0-59ac2c96227c"
   },
   "volume_fraction": null
}