{
   "conditions": [
      {
         "file_links": [],
         "name": "Location",
         "notes": null,
         "origin": "unknown",
         "template": {
            "id": "bc022dbd-c19d-4b8c-aedd-2f41f09d937f",
            "scope": "auto",
            "type": "link_by_uid"
         },
         "type": "condition",
         "value": {
            "category": "Wet Lab",
            "type": "nominal_categorical"
         }
      }
   ],
   "file_links": [],
   "name": "GBM1012 Dissolving Process",
   "notes": null,
   "parameters": [
      {
         "file_links": [],
         "name": "Equipment Used",
         "notes": null,
         "origin": "unknown",
         "template": {
            "id": "cd49e27d-8917-43a8-ae25-466f9e247f43",
            "scope": "auto",
            "type": "link_by_uid"
         },
         "type": "parameter",
         "value": {
            "category": "Vacuum Filter",
            "type": "nominal_categorical"
         }
      }
   ],
   "source": {
      "performed_by": "gmurra12@jh.edu",
      "performed_date": "2023-07-05T00:00:00",
      "type": "performed_source"
   },
   "spec": {
      "id": "3c2c5ab2-887f-4cb5-848f-d57fa5dff37e",
      "scope": "auto",
      "type": "link_by_uid"
   },
   "tags": [],
   "type": "process_run",
   "uids": {
      "auto": "3698d4d5-1eb0-488a-9990-c2ea78ad0802"
   }
}