{
   "absolute_quantity": {
      "nominal": 500.0,
      "type": "nominal_real",
      "units": "milligram"
   },
   "file_links": [],
   "labels": [],
   "mass_fraction": null,
   "material": {
      "id": "2b3de411-9c49-4042-8678-00630603af0b",
      "scope": "auto",
      "type": "link_by_uid"
   },
   "name": "GBM1003C Ingredient",
   "notes": null,
   "number_fraction": null,
   "process": {
      "id": "70e0fc84-09fe-4581-8d7e-e450f9615f4f",
      "scope": "auto",
      "type": "link_by_uid"
   },
   "spec": {
      "id": "52793245-40db-40f1-aa24-3621f75925a9",
      "scope": "auto",
      "type": "link_by_uid"
   },
   "tags": [],
   "type": "ingredient_run",
   "uids": {
      "auto": "c87d95a3-6c21-428b-bfc5-b7cf48eb9e01"
   },
   "volume_fraction": null
}